moana/.DS_Store
moana/__init__.py
moana/_version.py
moana/corner/LICENSE
moana/corner/__init__.py
moana/corner/tools.py
moana/david_bennett_fit/__init__.py
moana/david_bennett_fit/fitting_algorithm_parameters.py
moana/david_bennett_fit/instrument_parameters.py
moana/david_bennett_fit/lens_model_parameter.py
moana/david_bennett_fit/light_curve_with_instrument_parameters.py
moana/david_bennett_fit/names.py
moana/david_bennett_fit/run.py
moana/david_bennett_fit/runner.py
moana/dbc/__init__.py
moana/dbc/instruments.py
moana/dbc/io.py
moana/dbc/tools.py
moana/estimators.py
moana/external_format_io/__init__.py
moana/external_format_io/light_curve_file_liaison.py
moana/frames.py
moana/lens.py
moana/light_curve.py
moana/lookup.py
moana/stylelib/corner_plots_times.mplstyle
moana/viewer/.DS_Store
moana/viewer/__init__.py
moana/viewer/caustic_crossing_viewer.py
moana/viewer/caustic_topology_viewer.py
moana/viewer/color_mapper.py
moana/viewer/delta_chi_squared_viewer.py
moana/viewer/galatic_model_viewer.py
moana/viewer/light_curve_viewer.py
moana/viewer/run_fit_viewer.py
moana/viewer/run_modifier.py
moana_golmschenk-0.1.5.dist-info/LICENSE
moana_golmschenk-0.1.5.dist-info/WHEEL
moana_golmschenk-0.1.5.dist-info/METADATA
moana_golmschenk-0.1.5.dist-info/RECORD
