Metadata-Version: 2.1
Name: moana-golmschenk
Version: 0.1.5
Summary: 
Author: Greg Olmschenk
Author-email: golmschenk@gmail.com
Requires-Python: >=3.9,<3.10
Classifier: Programming Language :: Python :: 3
Classifier: Programming Language :: Python :: 3.9
Requires-Dist: backports-strenum (>=1.2.4,<2.0.0)
Requires-Dist: bokeh (>=2.3.1,<3.0.0)
Requires-Dist: file-read-backwards (>=2.0.0,<3.0.0)
Requires-Dist: matplotlib (>=3.7.0,<4.0.0)
Requires-Dist: numpy (>=1.23.0,<1.24.0)
Requires-Dist: pandas (>=1.5.3,<2.0.0)
Requires-Dist: scipy (>=1.6.2,<2.0.0)
Requires-Dist: tabulate (>=0.8.9,<0.9.0)
